domovoy_typing/__init__.py
domovoy_typing/apps.py
domovoy_typing/entities.py
domovoy_typing/services.py
domovoy_typing-2026.1.0.dist-info/METADATA
domovoy_typing-2026.1.0.dist-info/WHEEL
domovoy_typing-2026.1.0.dist-info/RECORD
