Metadata-Version: 2.4
Name: domovoy-typing
Version: 2026.1.0
Author: carlos-sarmiento
Requires-Python: >=3.14.2
Requires-Dist: domovoy>=0.10.0
